wave_1d_fd_perf
