Metadata-Version: 1.1
Name: wave-1d-fd-perf
Version: 0.0.11
Summary: Performance analysis of different implementations of 1d finite difference wave propagation
Home-page: https://github.com/ar4/wave_1d_fd_perf
Author: Alan Richardson
Author-email: alan@ausargeo.com
License: MIT
Platform: UNKNOWN
Classifier: Development Status :: 3 - Alpha
Classifier: Intended Audience :: Science/Research
Classifier: License :: OSI Approved :: MIT License
Classifier: Programming Language :: Python :: 2
Classifier: Programming Language :: Python :: 2.7
Classifier: Programming Language :: Python :: 3
Classifier: Programming Language :: Python :: 3.4
Classifier: Programming Language :: Python :: 3.5
